mean_opinion_score/__init__.py
mean_opinion_score/calculation.py
mean_opinion_score_tests/__init__.py
mean_opinion_score_tests/helper.py
mean_opinion_score_tests/calculation_py/__init__.py
mean_opinion_score_tests/calculation_py/test_get_ci95_blizzard_results.py
mean_opinion_score_tests/calculation_py/test_get_ci95_default_blizzard_results.py
mean_opinion_score_tests/calculation_py/test_get_custom_variance.py
mean_opinion_score_tests/calculation_py/test_get_mean_vertical_variance.py
mean_opinion_score_tests/calculation_py/test_get_mos.py
mean_opinion_score_tests/calculation_py/test_get_mos_blizzard_results.py
mean_opinion_score_tests/calculation_py/test_get_non_nan_count.py
mean_opinion_score_tests/calculation_py/test_get_v_mu.py
mean_opinion_score_tests/calculation_py/test_matlab_tinv.py
mean_opinion_score_tests/res/blizzard_crowdmos1_hp.json
mean_opinion_score_tests/res/blizzard_crowdmos2_hp.json
mean_opinion_score_tests/res/blizzard_crowdmos2_ls.json
mean_opinion_score_tests/res/blizzard_online_volunteers.json
mean_opinion_score_tests/res/blizzard_paid_participants.json
mean_opinion_score-0.0.2.dist-info/LICENSE
mean_opinion_score-0.0.2.dist-info/METADATA
mean_opinion_score-0.0.2.dist-info/WHEEL
mean_opinion_score-0.0.2.dist-info/top_level.txt
mean_opinion_score-0.0.2.dist-info/RECORD
