Metadata-Version: 2.1
Name: mean-opinion-score
Version: 0.0.2
Summary: Library for calculating the mean opinion score and 95% confidence interval of the standard deviation of text-to-speech ratings according to Ribeiro et al. (2011).
Author-email: Stefan Taubert <pypi@stefantaubert.com>
Maintainer-email: Stefan Taubert <pypi@stefantaubert.com>
License: MIT
Project-URL: Homepage, https://github.com/stefantaubert/mean-opinion-score
Project-URL: Issues, https://github.com/stefantaubert/mean-opinion-score/issues
Keywords: TTS,Text-to-speech,Speech synthesis,Mean Opinion Score,Language
Classifier: Development Status :: 2 - Pre-Alpha
Classifier: Operating System :: OS Independent
Classifier: Operating System :: MacOS
Classifier: Operating System :: POSIX
Classifier: Operating System :: POSIX :: BSD
Classifier: Operating System :: POSIX :: Linux
Classifier: Operating System :: Unix
Classifier: Operating System :: Microsoft :: Windows
Classifier: Programming Language :: Python
Classifier: Programming Language :: Python :: 3 :: Only
Classifier: Programming Language :: Python :: 3
Classifier: Programming Language :: Python :: 3.6
Classifier: Programming Language :: Python :: 3.7
Classifier: Programming Language :: Python :: 3.8
Classifier: Programming Language :: Python :: 3.9
Classifier: Programming Language :: Python :: 3.10
Classifier: Programming Language :: Python :: 3.11
Classifier: License :: OSI Approved :: MIT License
Requires-Python: <3.12,>=3.6
License-File: LICENSE
Requires-Dist: numpy
Requires-Dist: scipy
